pyscada/__init__.py
pyscada/systemstat/__init__.py
pyscada/systemstat/admin.py
pyscada/systemstat/apps.py
pyscada/systemstat/device.py
pyscada/systemstat/models.py
pyscada/systemstat/signals.py
pyscada/systemstat/worker.py
pyscada/systemstat/fixtures/systemstat.json
pyscada/systemstat/migrations/0001_initial.py
pyscada/systemstat/migrations/0002_auto_20160115_0918.py
pyscada/systemstat/migrations/0003_auto_20160927_1424.py
pyscada/systemstat/migrations/0004_auto_20170224_1250.py
pyscada/systemstat/migrations/0005_extendedsystemstatdevice_extendedsystemstatvariable.py
pyscada/systemstat/migrations/0006_auto_20170914_2110.py
pyscada/systemstat/migrations/0007_auto_20170916_1143.py
pyscada/systemstat/migrations/0008_auto_20191004_0912.py
pyscada/systemstat/migrations/0009_auto_20200901_1411.py
pyscada/systemstat/migrations/0010_auto_20200902_0813.py
pyscada/systemstat/migrations/0011_auto_20200914_1229.py
pyscada/systemstat/migrations/0012_auto_20200915_0931.py
pyscada/systemstat/migrations/0013_auto_20230202_1245.py
pyscada/systemstat/migrations/0014_auto_20230227_1421.py
pyscada/systemstat/migrations/0015_create_systemstat_device.py
pyscada/systemstat/migrations/0016_alter_systemstatvariable_information.py
pyscada/systemstat/migrations/0017_add_device_protocol.py
pyscada/systemstat/migrations/__init__.py
pyscada_systemstat-0.8.0.dist-info/AUTHORS
pyscada_systemstat-0.8.0.dist-info/LICENSE
pyscada_systemstat-0.8.0.dist-info/METADATA
pyscada_systemstat-0.8.0.dist-info/WHEEL
pyscada_systemstat-0.8.0.dist-info/top_level.txt
pyscada_systemstat-0.8.0.dist-info/RECORD
